gmenu/__init__.py
gmenu/admin.py
gmenu/apps.py
gmenu/menus.py
gmenu/models.py
gmenu/tests.py
gmenu/urls.py
gmenu/views.py
gmenu/migrations/0001_initial.py
gmenu/migrations/0002_auto_20210715_0618.py
gmenu/migrations/__init__.py
projmenu/__init__.py
projmenu/asgi.py
projmenu/settings.py
projmenu/urls.py
projmenu/wsgi.py
gmenu-0.0.3.dist-info/METADATA
gmenu-0.0.3.dist-info/WHEEL
gmenu-0.0.3.dist-info/license
gmenu-0.0.3.dist-info/top_level.txt
gmenu-0.0.3.dist-info/RECORD
